[
  {
    "postID": 21,
    "proID": 27,
    "proName": "2'li Makarna Menü",
    "proUnit": "Tam",
    "proStock": "0",
    "proPrice": "530,00 TL"
  },
  {
    "postID": 14,
    "proID": 17,
    "proName": "Tiramisu",
    "proUnit": "Tam",
    "proStock": "0",
    "proPrice": "200,00 TL"
  },
  {
    "postID": 13,
    "proID": 16,
    "proName": "Künefe",
    "proUnit": "Tam",
    "proStock": "0",
    "proPrice": "290,00 TL"
  },
  {
    "postID": 12,
    "proID": 15,
    "proName": "Limonata",
    "proUnit": "Tam",
    "proStock": "0",
    "proPrice": "85,00 TL"
  },
  {
    "postID": 11,
    "proID": 14,
    "proName": "Soda",
    "proUnit": "Tam",
    "proStock": "487",
    "proPrice": "45,00 TL"
  },
  {
    "postID": 10,
    "proID": 13,
    "proName": "Su",
    "proUnit": "Tam",
    "proStock": "160",
    "proPrice": "35,00 TL"
  },
  {
    "postID": 8,
    "proID": 11,
    "proName": "Çay",
    "proUnit": "Tam",
    "proStock": "0",
    "proPrice": "35,00 TL"
  },
  {
    "postID": 1,
    "proID": 1,
    "proName": "Limonlu Kremalı",
    "proUnit": "Tam",
    "proStock": "0",
    "proPrice": "389,00 TL"
  },
  {
    "postID": 9,
    "proID": 12,
    "proName": "Türk Kahvesi",
    "proUnit": "Tam",
    "proStock": "0",
    "proPrice": "85,00 TL"
  },
  {
    "postID": 7,
    "proID": 9,
    "proName": "Köri Tavuk",
    "proUnit": "Tam",
    "proStock": "0",
    "proPrice": "349,00 TL"
  },
  {
    "postID": 16,
    "proID": 20,
    "proName": "Acı Tavuk",
    "proUnit": "Tam",
    "proStock": "0",
    "proPrice": "349,00 TL"
  },
  {
    "postID": 17,
    "proID": 22,
    "proName": "Limonlu Alfredo",
    "proUnit": "Tam",
    "proStock": "0",
    "proPrice": "369,00 TL"
  },
  {
    "postID": 15,
    "proID": 18,
    "proName": "Pesto Soslu",
    "proUnit": "Tam",
    "proStock": "0",
    "proPrice": "319,00 TL"
  },
  {
    "postID": 2,
    "proID": 3,
    "proName": "Sade Makarna",
    "proUnit": "Tam",
    "proStock": "0",
    "proPrice": "160,00 TL"
  }
]
